{
  "name": "CH32V103C6T6",
  "family": "QingKe RISC-V-based, general-purpose MCU",
  "product_type": "QingKe V3/V4 core, basic version, main frequency <= 72M",
  "subfamily": "General-purpose",
  "packages": [
    {
      "name": "CH32V103C6T6",
      "package": "LQFP48"
    }
  ],
  "_raw": {
    "Part NO.": "CH32V103C6T6",
    "Freq": "80MHz",
    "Flash": "32K",
    "SRAM": "10K",
    "Package": "LQFP48",
    "GPIO": "37",
    "UART": "2",
    "IIC": "1",
    "DAC": "-",
    "SPI": "1/-",
    "OPA": "-",
    "ADC": "1/10",
    "Touchkey": "10",
    "Advanced TM": "1/2",
    "RTC": "1",
    "WDOG": "2",
    "USB_20": "H/D",
    "USB_20H": "-",
    "CAN": "-",
    "Ethernet": "-",
    "TRNG": "-",
    "SDIO": "-",
    "VDD": "3.3/5.0",
    "BLE": "-",
    "url": "http://www.wch.cn/products/CH32V103.html"
  },
  "memory": [
    {
      "name": "FLASH",
      "kind": "flash",
      "address": 0,
      "size": "32K",
      "settings": {
        "erase_size": 1024,
        "write_size": 64,
        "erase_value": 255
      }
    },
    {
      "name": "SRAM",
      "kind": "ram",
      "address": 536870912,
      "size": "10K"
    }
  ],
  "docs": [
    {
      "type": "homepage",
      "title": "Unknow",
      "name": "",
      "url": "http://www.wch.cn/products/CH32V103.html"
    },
    {
      "type": "demo_code",
      "title": "Unknow",
      "name": ""
    },
    {
      "type": "datasheet",
      "title": "Unknow",
      "name": "",
      "version": "1.0",
      "url": "TODO"
    },
    {
      "type": "reference_manual",
      "title": "Unknow",
      "name": "",
      "version": "1.0",
      "url": "TODO"
    }
  ],
  "cores": [
    {
      "name": "qingke-v4",
      "peripherals": [
        {
          "name": "GPIOA",
          "address": 1073741824,
          "registers": {
            "kind": "gpio",
            "version": "v2",
            "block": "GPIO",
            "configurations": {
              "lines": 16
            }
          },
          "rcc": {
            "clock": "GPIO",
            "enable": {
              "register": "GPIOENR",
              "field": "GPIOAEN"
            },
            "reset": {
              "register": "GPIORSTR",
              "field": "GPIOARST"
            }
          }
        }
      ],
      "interrupts": [
        {
          "name": "WWDG",
          "number": 1
        }
      ],
      "dma_channels": [
        {
          "name": "DMA1_CH1",
          "dma": "DMA1",
          "channel": 0
        }
      ]
    }
  ]
}